kengerkit/__init__.py
kengerkit/client.py
kengerkit/config.py
kengerkit/email.py
kengerkit/exceptions.py
kengerkit/http.py
kengerkit/registry.py
kengerkit-0.2.1.dist-info/METADATA
kengerkit-0.2.1.dist-info/WHEEL
kengerkit-0.2.1.dist-info/top_level.txt
kengerkit-0.2.1.dist-info/RECORD
