Metadata-Version: 2.1
Name: kengerkit
Version: 0.2.1
Summary: Kenger Service Python SDK
Home-page: https://github.com/xiaoyu-ai/kengerkit
Author: kenger
Author-email: kengerlwl@qq.com
Classifier: Programming Language :: Python :: 3
Classifier: Programming Language :: Python :: 3.7
Classifier: Programming Language :: Python :: 3.8
Classifier: Programming Language :: Python :: 3.9
Classifier: Programming Language :: Python :: 3.10
Classifier: Programming Language :: Python :: 3.11
Classifier: License :: OSI Approved :: MIT License
Classifier: Operating System :: OS Independent
Requires-Python: >=3.7
Requires-Dist: requests>=2.25.0
